{
	"date": 180120000,
	"events": [{
		"day": 13,
		"dayEnd": 14,
		"description": "Come and eat fruits with Kula to get rewards! ",
		"month": "Nov.",
		"month_id": 11,
		"name": "Kula's Fruits Adventure. ",
		"eveimgurl": ""
	}, {
		"day": 13,
		"dayEnd": 14,
		"description": "Gold Rush challenge chance+2 during the event! Come challenge Gold Rush stages! ",
		"month_id": 11,
		"month": "Nov.",
		"name": "Gold Rush Chance+2. ",
		"eveimgurl": "https://www.mxl-apps.com/ugkof98api_staging/api/v1/../../assets/images/events/event_gold_rush.png"
	}, {
		"day": 13,
		"dayEnd": 14,
		"description": "Promotion Gem exchange during the event, come join it! ",
		"month_id": 11,
		"month": "Nov.",
		"name": "Promotion Gem Exchange. ",
		"eveimgurl": "https://www.mxl-apps.com/ugkof98api_staging/api/v1/../../assets/images/events/event_promotion_gem_exchange.png"
	}, {
		"day": 13,
		"dayEnd": 15,
		"description": "Equipment pack can increase Clark XIII to:",
		"month_id": 11,
		"month": "Nov.",
		"name": "Fighter Equipment Pack (Clark XIII). ",
		"eveimgurl": "https://www.mxl-apps.com/ugkof98api_staging/api/v1/../../assets/images/events/event_fighter_equipment.png"
	}, {
		"day": 13,
		"dayEnd": 15,
		"description": "Upgrade pack can increase Clark XIII to:",
		"month_id": 11,
		"month": "Nov.",
		"name": "Fighter Upgrade Pack (Clark XIII). ",
		"eveimgurl": "https://www.mxl-apps.com/ugkof98api_staging/api/v1/../../assets/images/events/event_fighter_upgrade.png"
	}, {
		"day": 13,
		"dayEnd": 15,
		"description": "During the event, Fighter Weapon Awakening Frag Pack is available for limited time. Get it now!",
		"month_id": 11,
		"month": "Nov.",
		"name": "Fighter Weapon Awakening Frag Pack Exchange. ",
		"eveimgurl": ""
	}, {
		"day": 13,
		"dayEnd": 18,
		"description": "",
		"month_id": 11,
		"month": "Nov.",
		"name": "Time-limited Chest (Clark XIII). ",
		"eveimgurl": "https://www.mxl-apps.com/ugkof98api_staging/api/v1/../../assets/images/events/event_time_limited_chest.png"
	}, {
		"day": 13,
		"dayEnd": 18,
		"description": "Spend Diamonds to a specified amount during the event and get awesome rewards!",
		"month_id": 11,
		"month": "Nov.",
		"name": "Spend for Rewards. ",
		"eveimgurl": "https://www.mxl-apps.com/ugkof98api_staging/api/v1/../../assets/images/events/event_Spend_rewards.png"
	}, {
		"day": 14,
		"dayEnd": 15,
		"description": "Pop Balloons is unlocked during the event. Hit the balloon accurately to get rich rewards!",
		"month_id": 11,
		"month": "Nov.",
		"name": "Pop Balloons. ",
		"eveimgurl": "https://www.mxl-apps.com/ugkof98api_staging/api/v1/../../assets/images/events/event_pop_balloons.png"
	}, {
		"day": 14,
		"dayEnd": 15,
		"description": "Defeat the Igniz clones a certain number of times during the event to get Igniz[Frag].",
		"month_id": 11,
		"month": "Nov.",
		"name": "Team Battle to get Igniz. ",
		"eveimgurl": "https://www.mxl-apps.com/ugkof98api_staging/api/v1/../../assets/images/events/event_clone.png"
	}, {
		"day": 14,
		"dayEnd": 16,
		"description": "Accumulate certain ultimate trial points during the event and claim extra rewards! (Daily Reset)",
		"month_id": 11,
		"month": "Nov.",
		"name": "Rewards for Trial Points. ",
		"eveimgurl": "https://www.mxl-apps.com/ugkof98api_staging/api/v1/../../assets/images/events/event_trial_point.png"
	}, {
		"day": 14,
		"dayEnd": 15,
		"description": "",
		"month_id": 11,
		"month": "Nov.",
		"name": "Time-limited Resource Exchange. ",
		"eveimgurl": "https://www.mxl-apps.com/ugkof98api_staging/api/v1/../../assets/images/events/event_fighter_frag_exchange.png"
	}, {
		"day": 15,
		"dayEnd": 16,
		"description": "Aircraft Game is here, take your fight into the sky, let's go!",
		"month_id": 11,
		"month": "Nov.",
		"name": "Mini game-Aircraft. ",
		"eveimgurl": "https://www.mxl-apps.com/ugkof98api_staging/api/v1/../../assets/images/events/event_Aircraft_Game.png"
	}, {
		"day": 15,
		"dayEnd": 16,
		"description": "Defeat the Kula clones a certain number of times during the event to get Kula[Frag].",
		"month_id": 11,
		"month": "Nov.",
		"name": "Team Battle to get Kula. ",
		"eveimgurl": "https://www.mxl-apps.com/ugkof98api_staging/api/v1/../../assets/images/events/event_clone.png"
	}, {
		"day": 15,
		"dayEnd": 18,
		"description": "Achieve certain number of stars in Abyss Campaign to get rewards!",
		"month_id": 11,
		"month": "Nov.",
		"name": "Campaign Reward. ",
		"eveimgurl": "https://www.mxl-apps.com/ugkof98api_staging/api/v1/../../assets/images/events/event_campaing_master_abyss.png"
	}, {
		"day": 15,
		"dayEnd": 18,
		"description": "During the event, participate in the FightSoul Wish and there is a chance to get rewards including FightSoul Book Frags, Awakening Gems, and Power Fragment Chests.",
		"month_id": 11,
		"month": "Nov.",
		"name": "FightSoul Wish. ",
		"eveimgurl": "https://www.mxl-apps.com/ugkof98api_staging/api/v1/../../assets/images/events/event_FS_wish.png"
	}, {
		"day": 15,
		"dayEnd": 16,
		"description": "",
		"month_id": 11,
		"month": "Nov.",
		"name": "Time-limited Gift Pack. ",
		"eveimgurl": ""
	}, {
		"day": 15,
		"dayEnd": 16,
		"description": "BOSS Fighter cuisine is available in Mystic store during the event.",
		"month_id": 11,
		"month": "Nov.",
		"name": "Mystic Store. ",
		"eveimgurl": "https://www.mxl-apps.com/ugkof98api_staging/api/v1/../../assets/images/events/event_mystic_store.png"
	}, {
		"day": 15,
		"dayEnd": 18,
		"description": "Use Egg Machine during the event, and there is a chance for you to get Clark XIII Awaken Weapon Frag, Tome, Badge and other rare items.",
		"month_id": 11,
		"month": "Nov.",
		"name": "Weapons Egg Machine. ",
		"eveimgurl": "https://www.mxl-apps.com/ugkof98api_staging/api/v1/../../assets/images/events/event_weapon_egg.png"
	}, {
		"day": 16,
		"dayEnd": 17,
		"description": "Kyo's Tower Drop is available during the event. Get rich rewards with your wit!",
		"month_id": 11,
		"month": "Nov.",
		"name": "Kyo's Tower Drop. ",
		"eveimgurl": "https://www.mxl-apps.com/ugkof98api_staging/api/v1/../../assets/images/events/event_tower.png"
	}, {
		"day": 16,
		"dayEnd": 17,
		"description": "Mirage Challenge chance+2 during the event! Come and challenge Mirage Challenge stages!",
		"month_id": 11,
		"month": "Nov.",
		"name": "Mirage Challenge Chance+2. ",
		"eveimgurl": "https://www.mxl-apps.com/ugkof98api_staging/api/v1/../../assets/images/events/event_mirage.png"
	}, {
		"day": 16,
		"dayEnd": 18,
		"description": "Opening hidden safes in Ultimate Trials for double Golds, come get it now! (Only doubled for free tries) (Daily Reset)",
		"month_id": 11,
		"month": "Nov.",
		"name": "Double Gold in Trial Hidden Safe. ",
		"eveimgurl": "https://www.mxl-apps.com/ugkof98api_staging/api/v1/../../assets/images/events/event_double_gold_trial.png"
	}, {
		"day": 16,
		"dayEnd": 17,
		"description": "Tome and Tome material can be exchanged for one another during the event, please take note that each Tome can only be exchanged once, choose carefully!",
		"month_id": 11,
		"month": "Nov.",
		"name": "Tome Exchange. ",
		"eveimgurl": "https://www.mxl-apps.com/ugkof98api_staging/api/v1/../../assets/images/events/event_tome_exange.png"
	}, {
		"day": 16,
		"dayEnd": 18,
		"description": "Exchange for the fighter fragments you need now, don't miss this rare opportunity!",
		"month_id": 11,
		"month": "Nov.",
		"name": "Fighter Fragment Exchange. ",
		"eveimgurl": "https://www.mxl-apps.com/ugkof98api_staging/api/v1/../../assets/images/events/event_fighter_frag_exchange.png"
	}, {
		"day": 17,
		"dayEnd": 18,
		"description": "What treasures can you dig up from Ash Secret Garden? Come check it out!",
		"month_id": 11,
		"month": "Nov.",
		"name": "Ash Secret Garden. ",
		"eveimgurl": "https://www.mxl-apps.com/ugkof98api_staging/api/v1/../../assets/images/events/event_Secret_Garden.png"
	}, {
		"day": 17,
		"dayEnd": 18,
		"description": "Female Fighters Challenge chance+2 during the event! Come challenge Female Fighters Challenge stages! ",
		"month_id": 11,
		"month": "Nov.",
		"name": "Female Fighters Challenge Chance+2. ",
		"eveimgurl": "https://www.mxl-apps.com/ugkof98api_staging/api/v1/../../assets/images/events/event_female.png"
	}, {
		"day": 17,
		"dayEnd": 18,
		"description": "Badge and Badge Material can be exchanged for one another during the event, please take note that each Badge can only be exchanged once, choose carefully!",
		"month_id": 11,
		"month": "Nov.",
		"name": "Badge Exchange. ",
		"eveimgurl": "https://www.mxl-apps.com/ugkof98api_staging/api/v1/../../assets/images/events/event_badge_exchange.png"
	}, {
		"day": 18,
		"dayEnd": 19,
		"description": "What are you waiting for, come challenge it now, be the first to get 2048!",
		"month_id": 11,
		"month": "Nov.",
		"name": "2048 Challenge. ",
		"eveimgurl": "https://www.mxl-apps.com/ugkof98api_staging/api/v1/../../assets/images/events/event_2048.png"
	}, {
		"day": 18,
		"dayEnd": 19,
		"description": "Defeat the Orochi Leona clones a certain number of times during the event to get Orochi Leona[Frag].",
		"month_id": 11,
		"month": "Nov.",
		"name": "Team Battle to get Orochi Leona. ",
		"eveimgurl": "https://www.mxl-apps.com/ugkof98api_staging/api/v1/../../assets/images/events/event_clone.png"
	}, {
		"day": 18,
		"dayEnd": 20,
		"description": "",
		"month_id": 11,
		"month": "Nov.",
		"name": "Campaign Master. ",
		"eveimgurl": "https://www.mxl-apps.com/ugkof98api_staging/api/v1/../../assets/images/events/event_campaing_master_main.png"
	}, {
		"day": 19,
		"dayEnd": 20,
		"description": "Kensou eats Buns during the event. Play the game and claim rewards!",
		"month_id": 11,
		"month": "Nov.",
		"name": "Mini game-Eat Buns. ",
		"eveimgurl": ""
	}, {
		"day": 19,
		"dayEnd": 20,
		"description": "EXP Rush Challenge chance+2 during the event! Come challenge EXP Rush Challenge stages! ",
		"month_id": 11,
		"month": "Nov.",
		"name": "EXP Rush Challenge Chance+2. ",
		"eveimgurl": "https://www.mxl-apps.com/ugkof98api_staging/api/v1/../../assets/images/events/event_EXP_Rush.png"
	}, {
		"day": 20,
		"dayEnd": 21,
		"description": "Kula Defense War is unlocked during the event, test your speed and claim great rewards!",
		"month_id": 11,
		"month": "Nov.",
		"name": "Kula Defense War. ",
		"eveimgurl": "https://www.mxl-apps.com/ugkof98api_staging/api/v1/../../assets/images/events/event_defense_war.png"
	}, {
		"day": 20,
		"dayEnd": 21,
		"description": "Gold Rush challenge chance+2 during the event! Come challenge Gold Rush stages! ",
		"month_id": 11,
		"month": "Nov.",
		"name": "Gold Rush Chance+2. ",
		"eveimgurl": "https://www.mxl-apps.com/ugkof98api_staging/api/v1/../../assets/images/events/event_gold_rush.png"
	}, {
		"day": 20,
		"dayEnd": 22,
		"description": "Accumulate arena points during the event and claim extra rewards! (Daily Reset)",
		"month_id": 11,
		"month": "Nov.",
		"name": "Rewards for Arena Points. ",
		"eveimgurl": "https://www.mxl-apps.com/ugkof98api_staging/api/v1/../../assets/images/events/event_arena_points.png"
	}, {
		"day": 21,
		"dayEnd": 22,
		"description": "Train your superpower by charging the crystal ball and get rewards! ",
		"month_id": 11,
		"month": "Nov.",
		"name": "Superpower Drill . ",
		"eveimgurl": ""
	}, {
		"day": 21,
		"dayEnd": 22,
		"description": "Defeat the Instinct Iori clones a certain number of times during the event to get Instinct Iori[Frag].",
		"month_id": 11,
		"month": "Nov.",
		"name": "Team Battle to get Instinct Iori. ",
		"eveimgurl": "https://www.mxl-apps.com/ugkof98api_staging/api/v1/../../assets/images/events/event_clone.png"
	}, {
		"day": 21,
		"dayEnd": 23,
		"description": "Rune Converter is unlocked for limited time. It's up to you to decide your own runes!",
		"month_id": 11,
		"month": "Nov.",
		"name": "Rune Converter. ",
		"eveimgurl": "https://www.mxl-apps.com/ugkof98api_staging/api/v1/../../assets/images/events/event_rune_converter.png"
	}, {
		"day": 21,
		"dayEnd": 23,
		"description": "Hot Runes event is unlocked, come get it and increase your power now!",
		"month_id": 11,
		"month": "Nov.",
		"name": "Hot Runes. ",
		"eveimgurl": "https://www.mxl-apps.com/ugkof98api_staging/api/v1/../../assets/images/events/event_rune_converter.png"
	}, {
		"day": 21,
		"dayEnd": 24,
		"description": "Aid Doll Machine is unlocked! The Aid Souls of Robert 2002 UM, Benimaru 2003, and Adelheid are waiting for you to get!",
		"month_id": 11,
		"month": "Nov.",
		"name": "Aid Doll Machine. ",
		"eveimgurl": "https://www.mxl-apps.com/ugkof98api_staging/api/v1/../../assets/images/events/event_aid_doll_machine.png"
	}, {
		"day": 21,
		"dayEnd": 24,
		"description": "During the event, Fighter's Aid Pack is unlocked for limited time! Get it now!",
		"month_id": 11,
		"month": "Nov.",
		"name": "Aid Pack Exchange. ",
		"eveimgurl": "https://www.mxl-apps.com/ugkof98api_staging/api/v1/../../assets/images/events/event_aid_pack.png"
	}, {
		"day": 21,
		"dayEnd": 24,
		"description": "During the event, Aid Skill Book is unlocked for limited time! Get it now!",
		"month_id": 11,
		"month": "Nov.",
		"name": "Aid Skill Book Exchange. ",
		"eveimgurl": ""
	}, {
		"day": 21,
		"dayEnd": 24,
		"description": "Spend Diamonds to a specified amount during the event and get awesome rewards!",
		"month_id": 11,
		"month": "Nov.",
		"name": "Spend for Rewards. ",
		"eveimgurl": "https://www.mxl-apps.com/ugkof98api_staging/api/v1/../../assets/images/events/event_Spend_rewards.png"
	}, {
		"day": 22,
		"dayEnd": 23,
		"description": "Super Gold Scratcher is here, who knows what you may get!",
		"month_id": 11,
		"month": "Nov.",
		"name": "Super Scratcher. ",
		"eveimgurl": "https://www.mxl-apps.com/ugkof98api_staging/api/v1/../../assets/images/events/event_super_scratcher.png"
	}, {
		"day": 22,
		"dayEnd": 23,
		"description": "Defeat the Crazy Iori clones a certain number of times during the event to get Crazy Iori[Frag].",
		"month_id": 11,
		"month": "Nov.",
		"name": "Team Battle to get Crazy Iori. ",
		"eveimgurl": "https://www.mxl-apps.com/ugkof98api_staging/api/v1/../../assets/images/events/event_clone.png"
	}, {
		"day": 22,
		"dayEnd": 24,
		"description": "During the event, Elite Campaign chances+3, go challenge and get the fighter fragment you need now! ",
		"month_id": 11,
		"month": "Nov.",
		"name": "Elite Campaign Chances+3. ",
		"eveimgurl": "https://www.mxl-apps.com/ugkof98api_staging/api/v1/../../assets/images/events/event_campaing_master_elite.png"
	}, {
		"day": 22,
		"dayEnd": 24,
		"description": "Double SP for the first 5 purchases during the event! (Daily Reset)",
		"month_id": 11,
		"month": "Nov.",
		"name": "Double SP for first 5 purchases. ",
		"eveimgurl": "https://www.mxl-apps.com/ugkof98api_staging/api/v1/../../assets/images/events/event_sp_double.png"
	}, {
		"day": 23,
		"dayEnd": 24,
		"description": "Welcome to Shermie Adventure. Embark on a fun filled adventure with Shermie and find amazing treasures.",
		"month_id": 11,
		"month": "Nov.",
		"name": "Shermie Adventure. ",
		"eveimgurl": "https://www.mxl-apps.com/ugkof98api_staging/api/v1/../../assets/images/events/event_ShermiAdv.png"
	}, {
		"day": 23,
		"dayEnd": 24,
		"description": "Mirage Challenge chance+2 during the event! Come and challenge Mirage Challenge stages!",
		"month_id": 11,
		"month": "Nov.",
		"name": "Mirage Challenge Chance+2. ",
		"eveimgurl": "https://www.mxl-apps.com/ugkof98api_staging/api/v1/../../assets/images/events/event_mirage.png"
	}, {
		"day": 24,
		"dayEnd": 25,
		"description": "Mini game - Seal Orochi is unlocked! Come help seal orochi Now!",
		"month_id": 11,
		"month": "Nov.",
		"name": "Minigame - Seal Orochi. ",
		"eveimgurl": "https://www.mxl-apps.com/ugkof98api_staging/api/v1/../../assets/images/events/event_seal_orochi.png"
	}, {
		"day": 24,
		"dayEnd": 25,
		"description": "Female Fighters Challenge chance+2 during the event! Come challenge Female Fighters Challenge stages! ",
		"month_id": 11,
		"month": "Nov.",
		"name": "Female Fighters Challenge Chance+2. ",
		"eveimgurl": "https://www.mxl-apps.com/ugkof98api_staging/api/v1/../../assets/images/events/event_female.png"
	}, {
		"day": 24,
		"dayEnd": 26,
		"description": "Complete certain tasks for rewards during the event! (Daily Reset)",
		"month_id": 11,
		"month": "Nov.",
		"name": "Refine Blessing for Rewards. ",
		"eveimgurl": "https://www.mxl-apps.com/ugkof98api_staging/api/v1/../../assets/images/events/event_refine_blessing.png"
	}, {
		"day": 24,
		"dayEnd": 26,
		"description": "Time-limited Fighter Fashion is on sale! Come and get some new fashion for your fighters!",
		"month_id": 11,
		"month": "Nov.",
		"name": "Fighter Fashion Sale. ",
		"eveimgurl": "https://www.mxl-apps.com/ugkof98api_staging/api/v1/../../assets/images/events/event_rare_fashion_exchange.png"
	}, {
		"day": 24,
		"dayEnd": 26,
		"description": "Get BOSS Coin through the event to exchange for mighty BOSS fighters! What are you waiting for?",
		"month_id": 11,
		"month": "Nov.",
		"name": "BOSS Exchange. ",
		"eveimgurl": ""
	}, {
		"day": 24,
		"dayEnd": 28,
		"description": "Come to Shake&Shake, a lot of amazing rewards are waiting for you! (Daily Reset)",
		"month_id": 11,
		"month": "Nov.",
		"name": "Shake&Shake. ",
		"eveimgurl": ""
	}, {
		"day": 25,
		"dayEnd": 26,
		"description": "Come and eat fruits with Kula to get rewards! ",
		"month_id": 11,
		"month": "Nov.",
		"name": "Kula's Fruits Adventure. ",
		"eveimgurl": ""
	}, {
		"day": 25,
		"dayEnd": 26,
		"description": "Defeat the Mukai clones a certain number of times during the event to get Mukai[Frag].",
		"month_id": 11,
		"month": "Nov.",
		"name": "Team Battle to get Mukai. ",
		"eveimgurl": "https://www.mxl-apps.com/ugkof98api_staging/api/v1/../../assets/images/events/event_clone.png"
	}, {
		"day": 26,
		"dayEnd": 27,
		"description": "Pop Balloons is unlocked during the event. Hit the balloon accurately to get rich rewards!",
		"month_id": 11,
		"month": "Nov.",
		"name": "Pop Balloons. ",
		"eveimgurl": "https://www.mxl-apps.com/ugkof98api_staging/api/v1/../../assets/images/events/event_pop_balloons.png"
	}, {
		"day": 26,
		"dayEnd": 27,
		"description": "EXP Rush Challenge chance+2 during the event! Come challenge EXP Rush Challenge stages! ",
		"month_id": 11,
		"month": "Nov.",
		"name": "EXP Rush Challenge Chance+2. ",
		"eveimgurl": "https://www.mxl-apps.com/ugkof98api_staging/api/v1/../../assets/images/events/event_EXP_Rush.png"
	}, {
		"day": 26,
		"dayEnd": 28,
		"description": "Challenge Biography to a certain number of times to gain valuable rewards during the event. (Daily Reset)",
		"month_id": 11,
		"month": "Nov.",
		"name": "Biography Challenge Gift. ",
		"eveimgurl": "https://www.mxl-apps.com/ugkof98api_staging/api/v1/../../assets/images/events/event_biography.png"
	}, {
		"day": 26,
		"dayEnd": 28,
		"description": "During the event, open Esoteric Chest for a certain number of times to gain extra rewards!",
		"month_id": 11,
		"month": "Nov.",
		"name": "Draw Esoteric Stone for rewards. ",
		"eveimgurl": "https://www.mxl-apps.com/ugkof98api_staging/api/v1/../../assets/images/events/event_draw_esoteric.png"
	}, {
		"day": 26,
		"dayEnd": 28,
		"description": "Exchange for ULT Esoteric Stones during the event, don't miss out! (Daily Reset)",
		"month_id": 11,
		"month": "Nov.",
		"name": "ULT Esoteric Stone Limited Exchange. ",
		"eveimgurl": "https://www.mxl-apps.com/ugkof98api_staging/api/v1/../../assets/images/events/event_ULT_Esoteric_Chest.png"
	}, {
		"day": 26,
		"dayEnd": 28,
		"month_id": 11,
		"month": "Nov.",
		"name": "ULT Esoteric Exchange. ",
		"eveimgurl": "https://www.mxl-apps.com/ugkof98api_staging/api/v1/../../assets/images/events/event_esoteric_exchange.png"
	}, {
		"day": 26,
		"dayEnd": 28,
		"description": "During the event, you can use Red Esoteric Orig Stone to exchange ULT Esoteric Stone! ",
		"month_id": 11,
		"month": "Nov.",
		"name": "ULT Esoteric Exchange. ",
		"eveimgurl": "https://www.mxl-apps.com/ugkof98api_staging/api/v1/../../assets/images/events/event_esoteric_exchange.png"
	}, {
		"day": 26,
		"dayEnd": 28,
		"description": "During the event, you can exchange certain Orange Esoteric Stone for Orange Esoteric Stone[frag]! ",
		"month_id": 11,
		"month": "Nov.",
		"name": "Orange Esoteric Exchange. ",
		"eveimgurl": "https://www.mxl-apps.com/ugkof98api_staging/api/v1/../../assets/images/events/event_esoteric_exchange.png"
	},
		  {
		"day": 18,
		"dayEnd": 24,
		"description": "Login every day to get Thanksgiving Balloons during Thanksgiving season. Balloons can be exchanged for rare items, remember to login every day!",
		"month": "Nov.",
		"month_id": 11,
		"name": "Thanksgiving Login Rewards. ",
		"eveimgurl": ""
	}, {
		"day": 18,
		"dayEnd": 21,
		"description": "Complete Transcendence K' Task during the event to get special rewards!",
		"month_id": 11,
		"month": "Nov.",
		"name": "Transcendence K' Time-limited Task. ",
		"eveimgurl": ""
	}, {
		"day": 18,
		"dayEnd": 21,
		"description": "Complete Transcendence K' theme task during the event to get Transcendence K' Weapon Pack!",
		"month_id": 11,
		"month": "Nov.",
		"name": "Transcendence K' Theme Task. ",
		"eveimgurl": ""
	}, {
		"day": 18,
		"dayEnd": 21,
		"description": "Transcendence K' Pack is on sale for a limited time! You can't miss this opportunity!",
		"month_id": 11,
		"month": "Nov.",
		"name": "Transcendence K' Pack On Sale. ",
		"eveimgurl": ""
	}, {
		"day": 18,
		"dayEnd": 21,
		"description": "Recharge up to a specified amount in a single recharge during Thanksgiving season to get valuable rewards!",
		"month_id": 11,
		"month": "Nov.",
		"name": "Thanksgiving Single Recharge. ",
		"eveimgurl": ""
	}, {
		"day": 24,
		"dayEnd": 28,
		"description": "Complete the tasks during Thanksgiving season to get Thanksgiving Balloons! What are you waiting for?",
		"month_id": 11,
		"month": "Nov.",
		"name": "Thanksgiving Special Task. ",
		"eveimgurl": ""
	}, {
		"day": 24,
		"dayEnd": 30,
		"description": "Rare items are on sale at a discount during Thanksgiving season! Don't miss the chance!",
		"month_id": 11,
		"month": "Nov.",
		"name": "7. ",
		"eveimgurl": ""
	}, {
		"day": 24,
		"dayEnd": 28,
		"description": "Balloon Lucky Bags can be exchanged during Thanksgiving season! Come and test your luck!",
		"month_id": 11,
		"month": "Nov.",
		"name": "Thanksgiving Balloon Pack. ",
		"eveimgurl": ""
	}, {
		"day": 24,
		"dayEnd": 28,
		"description": "Use your Thanksgiving Balloons to exchange for rare items! Come and attend the event!",
		"month_id": 11,
		"month": "Nov.",
		"name": "Thanksgiving Balloon Exchange. ",
		"eveimgurl": ""
	}, {
		"day": 24,
		"dayEnd": 28,
		"description": "Recharge up to a specified amount during the event to get valuable Thanksgiving rewards!",
		"month_id": 11,
		"month": "Nov.",
		"name": "Thanksgiving Cumulative Recharge for Resource. ",
		"eveimgurl": ""
	}]
}
